.VERSION
AUTHORS.rst
CONTRIBUTING.rst
HISTORY.rst
LICENSE
MANIFEST.in
Pipfile
Pipfile.lock
README.rst
USAGE.rst
dev-requirements.txt
requirements.txt
setup.cfg
setup.py
docs/Makefile
docs/authors.rst
docs/conf.py
docs/contributing.rst
docs/history.rst
docs/index.rst
docs/installation.rst
docs/modules.rst
docs/readme.rst
docs/strava_api.rst
docs/stravapi.rst
docs/usage.rst
stravapi/.VERSION
stravapi/AUTHORS.rst
stravapi/CONTRIBUTING.rst
stravapi/HISTORY.rst
stravapi/LICENSE
stravapi/Pipfile
stravapi/Pipfile.lock
stravapi/README.rst
stravapi/USAGE.rst
stravapi/__init__.py
stravapi/_version.py
stravapi/client.py
stravapi/dev-requirements.txt
stravapi/requirements.txt
stravapi/stravapi.py
stravapi/stravapiexceptions.py
stravapi.egg-info/PKG-INFO
stravapi.egg-info/SOURCES.txt
stravapi.egg-info/dependency_links.txt
stravapi.egg-info/not-zip-safe
stravapi.egg-info/requires.txt
stravapi.egg-info/top_level.txt
stravapi/__pycache__/client.cpython-36.pyc